cattt/canvaskit_painter.py
cattt/color.py
cattt/core.py
cattt/frame.py
cattt/glfw_frame.py
cattt/sdl_frame.py
cattt/skia_painter.py
cattt/web_frame.py
cattt-0.1.4.dist-info/LICENSE
cattt-0.1.4.dist-info/WHEEL
cattt-0.1.4.dist-info/METADATA
cattt-0.1.4.dist-info/RECORD
