Metadata-Version: 2.1
Name: cattt
Version: 0.1.4
Summary: Cattt is a pure Python cross-platform UI framework
Home-page: https://github.com/i2y/cattt
License: MIT
Author: Yasushi Itoh
Author-email: i2y@icloud.com
Requires-Python: >=3.10,<4.0
Classifier: Development Status :: 2 - Pre-Alpha
Classifier: License :: OSI Approved :: MIT License
Classifier: Programming Language :: Python :: 3
Classifier: Programming Language :: Python :: 3.10
Classifier: Topic :: Software Development :: Libraries :: Python Modules
Provides-Extra: glfw
Provides-Extra: sdl
Requires-Dist: PyOpenGL (>=3.1.5,<4.0.0); extra == "glfw"
Requires-Dist: PySDL2 (>=0.9.11,<0.10.0); extra == "sdl"
Requires-Dist: darkdetect (>=0.5.1,<0.6.0); extra == "glfw" or extra == "sdl"
Requires-Dist: glcontext (>=2.3.6,<3.0.0); extra == "sdl"
Requires-Dist: glfw (>=2.5.3,<3.0.0); extra == "glfw"
Requires-Dist: pysdl2-dll (>=2.0.20,<3.0.0); extra == "sdl"
Requires-Dist: skia-python (>=87.4,<88.0); extra == "glfw" or extra == "sdl"
Requires-Dist: zengl (>=1.2.2,<2.0.0); extra == "sdl"
Project-URL: Documentation, https://i2y.github.io/cattt
Project-URL: Repository, https://github.com/i2y/cattt
